AUTHORS
LICENSE
README.md
setup.py
django_notifications_views/__init__.py
django_notifications_views/__version__.py
django_notifications_views/admin.py
django_notifications_views/app_settings.py
django_notifications_views/apps.py
django_notifications_views/expo_utils.py
django_notifications_views/models.py
django_notifications_views/serializers.py
django_notifications_views/tests.py
django_notifications_views/urls.py
django_notifications_views/views.py
django_notifications_views.egg-info/PKG-INFO
django_notifications_views.egg-info/SOURCES.txt
django_notifications_views.egg-info/dependency_links.txt
django_notifications_views.egg-info/not-zip-safe
django_notifications_views.egg-info/requires.txt
django_notifications_views.egg-info/top_level.txt
django_notifications_views/migrations/__init__.py