Metadata-Version: 2.1
Name: django_notifications_views
Version: 0.1.2
Summary: Django-notifications-views is an extension for Django-notifications-hq that provides a viewset for the notifications.
Home-page: https://github.com/nachoborrelli/Django-notifications-views
Author: nachoborrelli
Author-email: nacho2911@hotmail.com
License: MIT
Keywords: django notifications hq views
Classifier: Framework :: Django
Classifier: Intended Audience :: Developers
Classifier: Intended Audience :: System Administrators
Classifier: Operating System :: OS Independent
Classifier: Topic :: Software Development
Requires-Python: >=3.8
License-File: LICENSE
License-File: AUTHORS
Requires-Dist: Django>=3.8.0
Requires-Dist: pandas>=2.2.0
Requires-Dist: requests>=2.30
Requires-Dist: exponent-server-sdk~=2.0.0
Requires-Dist: django-notifications-hq~=1.8.0
